setup.py
Posit/__init__.py
Posit/main.py
Posit/utils/RMSD.py
Posit/utils/__init__.py
Posit/utils/prepare.py
posit.egg-info/PKG-INFO
posit.egg-info/SOURCES.txt
posit.egg-info/dependency_links.txt
posit.egg-info/entry_points.txt
posit.egg-info/requires.txt
posit.egg-info/top_level.txt
prepare/__init__.py
prepare/dry.py
prepare/extract_docking_result.py
prepare/wash_multi_ligands.py