Metadata-Version: 1.0
Name: posit
Version: 0.1.2
Summary: Pick a pose
Home-page: UNKNOWN
Author: Wenzhi Ma
Author-email: wenzhi.ma@xtalpi.com
License: UNKNOWN
Platform: UNKNOWN
